robot_kit/PCA9685.py
robot_kit/__init__.py
robot_kit/leds.py
robot_kit/ultrasonic.py
robot_kit/vehicle.py
robot_kit/wheels.py
robot_kit-0.1.5.data/data/examples/range_colors.py
robot_kit-0.1.5.data/data/examples/robot_start.py
robot_kit-0.1.5.dist-info/LICENSE
robot_kit-0.1.5.dist-info/METADATA
robot_kit-0.1.5.dist-info/WHEEL
robot_kit-0.1.5.dist-info/top_level.txt
robot_kit-0.1.5.dist-info/RECORD
