Metadata-Version: 2.1
Name: robot-kit
Version: 0.1.5
Summary: Robot Kit
Home-page: https://github.com/SuperCowPowers/robot_kit
Author: Brian Wylie
Author-email: briford@supercowpowers.com
License: Apache
Keywords: Robotics,Python
Platform: UNKNOWN
Classifier: Development Status :: 2 - Pre-Alpha
Classifier: Intended Audience :: Developers
Classifier: License :: OSI Approved :: Apache Software License
Classifier: Natural Language :: English
Classifier: Programming Language :: Python :: 3.6
Classifier: Programming Language :: Python :: 3.7
Classifier: Programming Language :: Python :: 3.8
Classifier: Programming Language :: Python :: Implementation :: CPython
Classifier: Programming Language :: Python :: Implementation :: PyPy
Requires-Dist: smbus
Requires-Dist: adafruit-circuitpython-neopixel
